wmain/__init__.py
wmain/mail/__init__.py
wmain/mail/email.py
wmain/mail/exceptions.py
wmain/mail/sender/__init__.py
wmain/mail/sender/client_brevo.py
wmain/mail/sender/ports/__init__.py
wmain/mail/sender/ports/smtp_sender_port.py
wmain/mail/sender/smtp_base.py
wmain/mail/sender/smtp_brevo.py
wmain_mail-0.1.2.dist-info/METADATA
wmain_mail-0.1.2.dist-info/WHEEL
wmain_mail-0.1.2.dist-info/RECORD
