Metadata-Version: 2.4
Name: wmain-mail
Version: 0.1.2
Summary: wmain 邮件包, 支持smtp, email等
License: MIT
Author: wmain-mail@wyn.wiki
Requires-Python: >=3.10,<4.0
Classifier: License :: OSI Approved :: MIT License
Classifier: Programming Language :: Python :: 3
Classifier: Programming Language :: Python :: 3.10
Classifier: Programming Language :: Python :: 3.11
Classifier: Programming Language :: Python :: 3.12
Classifier: Programming Language :: Python :: 3.13
Classifier: Programming Language :: Python :: 3.14
Requires-Dist: aiosmtplib (>=5.0.0,<6.0.0)
Requires-Dist: wmain-base (==0.1.1)
